prettyresults/__init__.py
prettyresults/crosses.py
prettyresults/dataloader.py
prettyresults/descriptives.py
prettyresults/result_tree.py
prettyresults/results.py
prettyresults/utils.py
prettyresults/word.py
prettyresults/web/angular-sanitize.min.js
prettyresults/web/angular.min.js
prettyresults/web/app.js
prettyresults/web/bootstrap.min.css
prettyresults/web/index.html
prettyresults/web/font-awesome-4.7.0/HELP-US-OUT.txt
prettyresults/web/font-awesome-4.7.0/css/font-awesome.css
prettyresults/web/font-awesome-4.7.0/css/font-awesome.min.css
prettyresults/web/font-awesome-4.7.0/fonts/FontAwesome.otf
prettyresults/web/font-awesome-4.7.0/fonts/fontawesome-webfont.eot
prettyresults/web/font-awesome-4.7.0/fonts/fontawesome-webfont.svg
prettyresults/web/font-awesome-4.7.0/fonts/fontawesome-webfont.ttf
prettyresults/web/font-awesome-4.7.0/fonts/fontawesome-webfont.woff
prettyresults/web/font-awesome-4.7.0/fonts/fontawesome-webfont.woff2
prettyresults/web/font-awesome-4.7.0/less/animated.less
prettyresults/web/font-awesome-4.7.0/less/bordered-pulled.less
prettyresults/web/font-awesome-4.7.0/less/core.less
prettyresults/web/font-awesome-4.7.0/less/fixed-width.less
prettyresults/web/font-awesome-4.7.0/less/font-awesome.less
prettyresults/web/font-awesome-4.7.0/less/icons.less
prettyresults/web/font-awesome-4.7.0/less/larger.less
prettyresults/web/font-awesome-4.7.0/less/list.less
prettyresults/web/font-awesome-4.7.0/less/mixins.less
prettyresults/web/font-awesome-4.7.0/less/path.less
prettyresults/web/font-awesome-4.7.0/less/rotated-flipped.less
prettyresults/web/font-awesome-4.7.0/less/screen-reader.less
prettyresults/web/font-awesome-4.7.0/less/stacked.less
prettyresults/web/font-awesome-4.7.0/less/variables.less
prettyresults/web/font-awesome-4.7.0/scss/_animated.scss
prettyresults/web/font-awesome-4.7.0/scss/_bordered-pulled.scss
prettyresults/web/font-awesome-4.7.0/scss/_core.scss
prettyresults/web/font-awesome-4.7.0/scss/_fixed-width.scss
prettyresults-1.0.0.dist-info/LICENSE.md
prettyresults-1.0.0.dist-info/METADATA
prettyresults-1.0.0.dist-info/WHEEL
prettyresults-1.0.0.dist-info/top_level.txt
prettyresults-1.0.0.dist-info/RECORD
