Metadata-Version: 2.1
Name: prettyresults
Version: 1.0.0
Summary: Present data analysis results in Web or Docx format
Home-page: https://github.com/anarthal/prettyresults
Author: Anarthal
Author-email: rubenperez038@gmail.com
License: UNKNOWN
Platform: UNKNOWN
Classifier: Programming Language :: Python :: 3 :: Only
Classifier: License :: OSI Approved :: MIT License
Classifier: Topic :: Scientific/Engineering
Requires-Dist: matplotlib (>=2.1.1)
Requires-Dist: numpy (>=1.13.3)
Requires-Dist: pandas (>=0.24.1)
Requires-Dist: python-docx (>=0.8.10)
Requires-Dist: scipy (>=0.19.1)
Requires-Dist: Pillow (>=5.1.0)
